README.md
setup.py
promptcloud/__init__.py
promptcloud/client.py
promptcloud/error.py
promptcloud/prompt.py
promptcloud/schema.py
promptcloud.egg-info/PKG-INFO
promptcloud.egg-info/SOURCES.txt
promptcloud.egg-info/dependency_links.txt
promptcloud.egg-info/requires.txt
promptcloud.egg-info/top_level.txt