Metadata-Version: 2.1
Name: promptcloud
Version: 1.0.1
Summary: Official python SDK for the PromptCloud API
Home-page: https://github.com/mattyhogan/PromptCloudPythonSDK
Author: Matty Hogan
Author-email: matthewhogan63@gmail.com
License: UNKNOWN
Platform: UNKNOWN
